<root>
	<player Deltacount="0" Deltadate="" Deltascore="100000" Highcount="30" Highdate="06.09.19 16:05" Highscore="97776" Lowcount="17" Lowdate="06.09.19 14:25" Lowscore="1" count="45" delta="10000" deltacount="0" deltadate="" name="korneliusdream" />
	<player Deltacount="0" Deltadate="" Deltascore="100000" Highcount="12" Highdate="06.09.19 16:18" Highscore="81526" Lowcount="7" Lowdate="06.09.19 15:58" Lowscore="382" count="15" name="makrooy" />
	<player Deltacount="0" Deltadate="" Deltascore="100000" Highcount="2" Highdate="06.09.19 13:58" Highscore="85048" Lowcount="1" Lowdate="06.09.19 13:44" Lowscore="2682" count="4" name="stantoncree_" />
	<player Deltacount="0" Deltadate="" Deltascore="100000" Highcount="7" Highdate="06.09.19 13:50" Highscore="96234" Lowcount="6" Lowdate="06.09.19 13:50" Lowscore="352" count="13" name="kem_" />
	<player Deltacount="0" Deltadate="" Deltascore="100000" Highcount="4" Highdate="06.09.19 13:54" Highscore="99410" Lowcount="17" Lowdate="06.09.19 16:26" Lowscore="1387" count="18" name="taylor131313" />
	<player Deltacount="0" Deltadate="" Deltascore="100000" Highcount="1" Highdate="06.09.19 13:49" Highscore="74308" Lowcount="2" Lowdate="06.09.19 14:01" Lowscore="30784" count="3" name="nsgr" />
	<player Deltacount="0" Deltadate="" Deltascore="100000" Highcount="7" Highdate="06.09.19 14:22" Highscore="96356" Lowcount="4" Lowdate="06.09.19 14:14" Lowscore="467" count="22" name="lackadal" />
	<player Deltacount="0" Deltadate="" Deltascore="100000" Highcount="2" Highdate="06.09.19 14:01" Highscore="46254" Lowcount="1" Lowdate="06.09.19 13:55" Lowscore="8690" count="2" name="pigge18652" />
	<player Deltacount="0" Deltadate="" Deltascore="100000" Highcount="1" Highdate="06.09.19 13:56" Highscore="45930" Lowcount="1" Lowdate="06.09.19 13:56" Lowscore="45930" count="1" name="spammiej" />
	<player Deltacount="0" Deltadate="" Deltascore="100000" Highcount="1" Highdate="06.09.19 14:04" Highscore="47508" Lowcount="1" Lowdate="06.09.19 14:04" Lowscore="47508" count="1" name="massa" />
	<player Deltacount="0" Deltadate="" Deltascore="100000" Highcount="1" Highdate="06.09.19 14:04" Highscore="1468" Lowcount="1" Lowdate="06.09.19 14:04" Lowscore="1468" count="1" name="bcp_" />
	<player Deltacount="0" Deltadate="" Deltascore="100000" Highcount="1" Highdate="06.09.19 14:06" Highscore="63152" Lowcount="1" Lowdate="06.09.19 14:06" Lowscore="63152" count="1" name="minatotm" />
	<player Deltacount="0" Deltadate="" Deltascore="100000" Highcount="2" Highdate="06.09.19 14:21" Highscore="19752" Lowcount="1" Lowdate="06.09.19 14:12" Lowscore="11431" count="2" name="actiiiiiive" />
	<player Deltacount="0" Deltadate="" Deltascore="100000" Highcount="1" Highdate="06.09.19 14:28" Highscore="60498" Lowcount="1" Lowdate="06.09.19 14:28" Lowscore="60498" count="1" name="mayhmeme" />
	<player Deltacount="0" Deltadate="" Deltascore="100000" Highcount="5" Highdate="06.09.19 16:12" Highscore="89190" Lowcount="3" Lowdate="06.09.19 15:59" Lowscore="4253" count="5" name="asteri" />
	<player Deltacount="0" Deltadate="" Deltascore="100000" Highcount="1" Highdate="06.09.19 14:54" Highscore="13511" Lowcount="2" Lowdate="06.09.19 15:27" Lowscore="4155" count="2" name="axelalex2" />
	<player Deltacount="0" Deltadate="" Deltascore="100000" Highcount="1" Highdate="06.09.19 14:55" Highscore="53087" Lowcount="2" Lowdate="06.09.19 15:56" Lowscore="44432" count="2" name="simplynick" />
	<player Deltacount="0" Deltadate="" Deltascore="100000" Highcount="2" Highdate="06.09.19 15:20" Highscore="74119" Lowcount="1" Lowdate="06.09.19 14:56" Lowscore="452" count="2" name="sparklingw" />
	<player Deltacount="0" Deltadate="" Deltascore="100000" Highcount="10" Highdate="06.09.19 16:22" Highscore="69154" Lowcount="6" Lowdate="06.09.19 15:35" Lowscore="1894" count="15" name="muffeyo" />
	<player Deltacount="0" Deltadate="" Deltascore="100000" Highcount="2" Highdate="06.09.19 15:28" Highscore="51821" Lowcount="1" Lowdate="06.09.19 15:13" Lowscore="47187" count="2" name="the2ndD6" />
	<player Deltacount="0" Deltadate="" Deltascore="100000" Highcount="1" Highdate="06.09.19 15:38" Highscore="84514" Lowcount="1" Lowdate="06.09.19 15:38" Lowscore="84514" count="1" name="rioluTM" />
	<player Deltacount="0" Deltadate="" Deltascore="100000" Highcount="1" Highdate="06.09.19 15:45" Highscore="19779" Lowcount="2" Lowdate="06.09.19 15:53" Lowscore="6690" count="2" name="phoebetm" />
	<player Deltacount="0" Deltadate="" Deltascore="100000" Highcount="1" Highdate="06.09.19 15:52" Highscore="22859" Lowcount="2" Lowdate="06.09.19 16:24" Lowscore="12507" count="2" name="s0ze47_" />
	<player Deltacount="0" Deltadate="" Deltascore="100000" Highcount="1" Highdate="06.09.19 15:52" Highscore="48518" Lowcount="1" Lowdate="06.09.19 15:52" Lowscore="48518" count="1" name="turtlezz" />
	<player Deltacount="0" Deltadate="" Deltascore="100000" Highcount="2" Highdate="06.09.19 16:05" Highscore="72988" Lowcount="1" Lowdate="06.09.19 15:58" Lowscore="30019" count="2" name="juvo" />
	<player Deltacount="0" Deltadate="" Deltascore="100000" Highcount="1" Highdate="06.09.19 16:00" Highscore="64232" Lowcount="1" Lowdate="06.09.19 16:00" Lowscore="64232" count="1" name="timaniaTM" />
	<player Deltacount="13" Deltadate="08.09.19 19:36" Deltascore="2709" Highcount="76" Highdate="22.09.19 11:56" Highscore="98029" Lowcount="23" Lowdate="15.09.19 16:20" Lowscore="9" count="81" name="hudlommen_" />
	<player Highcount="1" Highdate="23.09.19 17:31" Highscore="4554" Lowcount="1" Lowdate="23.09.19 17:31" Lowscore="4554" count="1" name="egokentrikosarouraios" />
	<player Highcount="1" Highdate="23.09.19 17:35" Highscore="7618" Lowcount="1" Lowdate="23.09.19 17:35" Lowscore="7618" count="1" name="egokentrikosarouraios" />
</root>